{
    "results": [
        {
            "drivers_cut": "45.72",
            "drivers_cut_converted": 45.72,
            "driver": null,
            "rating": null,
            "drivers_email": null,
            "delivered_confirmation": false,
            "delivered": false,
            "origin_city": "Cincinnati",
            "origin_state": "OH",
            "destination_state": "OH",
            "destination_city": "Cincinnati",
            "rated": false,
            "form_complete": true,
            "parent_pay": false,
            "user": "1591567803722x984057065615179900",
            "Created By": "1591567803722x984057065615179900",
            "receiver_name": null,
            "receiver_signature": null,
            "authorized": true,
            "active": true,
            "empty_travel_drivers_cut": null,
            "empty_travel": null,
            "drop_off_here": false,
            "origin_here": false,
            "shipper": "1591567803722x984057065615179900",
            "service_load_amount": 19.99,
            "service_load": true,
            "service_level": 1,
            "canceled": false,
            "reserved": false,
            "reserved_driver": null,
            "charged": false,
            "charged_failure": null,
            "date_accepted": null,
            "distance": 19.4,
            "distance_text": "19.4 mi",
            "origin_dimensions": "48x40x40",
            "vehicle_type": "Cargo Van",
            "match_id": "9AE4FF01",
            "coupon_code": null,
            "coupon_savings": null,
            "price_converted": 53.79,
            "created day": "6/07/20",
            "destination_address": {
                "address": "9691 Waterstone Blvd, Cincinnati, OH 45249, USA",
                "lat": 39.2949796,
                "lng": -84.3044488
            },
            "destination_notes": null,
            "origin_pieces": 5,
            "price": "53.79",
            "origin_weight": "100",
            "origin_address": {
                "address": "208 E 12th St, Cincinnati, OH 45202, USA",
                "lat": 39.1094281,
                "lng": -84.5111983
            },
            "origin_description": "Stuff",
            "Unique Key": "9ae4ff0183632fa8aa274d06088dbd51",
            "picked_up": false,
            "origin_photo": null,
            "picked_up_confirmation": false,
            "Created Date": "2020-06-07T22:17:27.857Z",
            "Modified Date": "2020-06-09T16:29:51.387Z",
            "recipient_phone": null,
            "recipient_name": null,
            "vehicle_class": 2,
            "drop_off_place": null,
            "pickup_place": null,
            "food": null,
            "pickup_notes": null,
            "schedule_dropoff": null,
            "scheduled_time": null,
            "service_load_amount_driver": 16.99,
            "shipper_name": " ",
            "shipper_phone": null,
            "_id": "1591568247844x426787066008459200"
        },
        {
            "drivers_cut": "26.24",
            "drivers_cut_converted": 26.24,
            "driver": null,
            "rating": null,
            "drivers_email": null,
            "delivered_confirmation": false,
            "delivered": false,
            "origin_city": "Florence",
            "origin_state": "KY",
            "destination_state": "KY",
            "destination_city": "Florence",
            "rated": false,
            "form_complete": true,
            "parent_pay": false,
            "user": "1506451003979x900442128768190700",
            "Created By": "1506451003979x900442128768190700",
            "receiver_name": null,
            "receiver_signature": null,
            "authorized": true,
            "active": true,
            "empty_travel_drivers_cut": null,
            "empty_travel": null,
            "drop_off_here": false,
            "origin_here": false,
            "shipper": "1506451003979x900442128768190700",
            "service_load_amount": 0,
            "service_load": false,
            "service_level": 1,
            "canceled": false,
            "reserved": false,
            "reserved_driver": null,
            "charged": false,
            "charged_failure": null,
            "date_accepted": null,
            "distance": 0,
            "distance_text": "0.0 mi",
            "origin_dimensions": "5x5x5",
            "vehicle_type": "Cargo Van",
            "match_id": "682E741A",
            "coupon_code": null,
            "coupon_savings": null,
            "price_converted": 34.99,
            "created day": "5/05/20",
            "destination_address": {
                "address": "636 Friars Ln, Florence, KY 41042, USA",
                "lat": 38.950607,
                "lng": -84.628626
            },
            "destination_notes": null,
            "origin_pieces": 5,
            "price": "34.99",
            "origin_weight": "25",
            "origin_address": {
                "address": "636 Friars Ln, Florence, KY 41042, USA",
                "lat": 38.950607,
                "lng": -84.628626
            },
            "origin_description": null,
            "Unique Key": "682e741a8f82f53b45d22dc3bf401ede",
            "picked_up": false,
            "origin_photo": null,
            "picked_up_confirmation": false,
            "Created Date": "2020-05-05T15:16:17.618Z",
            "Modified Date": "2020-05-05T15:16:38.979Z",
            "recipient_phone": "1",
            "recipient_name": null,
            "vehicle_class": 2,
            "drop_off_place": null,
            "pickup_place": null,
            "food": null,
            "pickup_notes": null,
            "schedule_dropoff": null,
            "scheduled_time": null,
            "service_load_amount_driver": 0,
            "shipper_name": "John Williams",
            "shipper_phone": "5135551289",
            "_id": "1588691777615x691906756444596200"
        }
    ],
    "cursor": 0,
    "count": 2,
    "remaining": 0
}